free_disk/__init__.py
free_disk-1.0.0.dist-info/LICENSE
free_disk-1.0.0.dist-info/METADATA
free_disk-1.0.0.dist-info/WHEEL
free_disk-1.0.0.dist-info/entry_points.txt
free_disk-1.0.0.dist-info/top_level.txt
free_disk-1.0.0.dist-info/RECORD
