Metadata-Version: 2.1
Name: free-disk
Version: 1.0.0
Summary: delete file with oldest modification date until a minimum of --free-bytes are available on disk
Home-page: https://github.com/fphammerle/free-disk
Author: Fabian Peter Hammerle
Author-email: fabian@hammerle.me
License: MIT
Keywords: disk,files,cleanup,free,delete,old
Platform: UNKNOWN
Classifier: Development Status :: 3 - Alpha
Classifier: Intended Audience :: System Administrators
Classifier: License :: OSI Approved :: MIT License
Classifier: Operating System :: POSIX
Classifier: Programming Language :: Python :: 3.7
Classifier: Programming Language :: Python :: 3.8
Classifier: Programming Language :: Python :: 3.9
Classifier: Programming Language :: Python :: 3.10
Classifier: Topic :: System :: Filesystems
Classifier: Topic :: Utilities
Requires-Python: >=3.7
